igap_bot/__init__.py
igap_bot/bot/__init__.py
igap_bot/bot/button.py
igap_bot/bot/client.py
igap_bot/bot/filters.py
igap_bot/bot/message.py
igap_bot/proto/BillInquiryMci_pb2.py
igap_bot/proto/BillInquiryTelecom_pb2.py
igap_bot/proto/ChannelAddAdmin_pb2.py
igap_bot/proto/ChannelAddMember_pb2.py
igap_bot/proto/ChannelAddMessageReaction_pb2.py
igap_bot/proto/ChannelAddModerator_pb2.py
igap_bot/proto/ChannelAvatarAdd_pb2.py
igap_bot/proto/ChannelAvatarDelete_pb2.py
igap_bot/proto/ChannelAvatarGetList_pb2.py
igap_bot/proto/ChannelCheckUsername_pb2.py
igap_bot/proto/ChannelCreate_pb2.py
igap_bot/proto/ChannelDeleteMessage_pb2.py
igap_bot/proto/ChannelDelete_pb2.py
igap_bot/proto/ChannelEditMessage_pb2.py
igap_bot/proto/ChannelEdit_pb2.py
igap_bot/proto/ChannelGetDraft_pb2.py
igap_bot/proto/ChannelGetMemberList_pb2.py
igap_bot/proto/ChannelGetMessagesStats_pb2.py
igap_bot/proto/ChannelKickAdmin_pb2.py
igap_bot/proto/ChannelKickMember_pb2.py
igap_bot/proto/ChannelKickModerator_pb2.py
igap_bot/proto/ChannelLeft_pb2.py
igap_bot/proto/ChannelPinMessage_pb2.py
igap_bot/proto/ChannelRemoveUsername_pb2.py
igap_bot/proto/ChannelRevokeLink_pb2.py
igap_bot/proto/ChannelSendMessage_pb2.py
igap_bot/proto/ChannelSetAction_pb2.py
igap_bot/proto/ChannelUpdateDraft_pb2.py
igap_bot/proto/ChannelUpdateReactionStatus_pb2.py
igap_bot/proto/ChannelUpdateSignature_pb2.py
igap_bot/proto/ChannelUpdateUsername_pb2.py
igap_bot/proto/ChatClearMessage_pb2.py
igap_bot/proto/ChatConvertToGroup_pb2.py
igap_bot/proto/ChatDeleteMessage_pb2.py
igap_bot/proto/ChatDelete_pb2.py
igap_bot/proto/ChatEditMessage_pb2.py
igap_bot/proto/ChatGetDraft_pb2.py
igap_bot/proto/ChatGetRoom_pb2.py
igap_bot/proto/ChatSendMessage_pb2.py
igap_bot/proto/ChatSetAction_pb2.py
igap_bot/proto/ChatUpdateDraft_pb2.py
igap_bot/proto/ChatUpdateStatus_pb2.py
igap_bot/proto/ClientCheckInviteLink_pb2.py
igap_bot/proto/ClientCondition_pb2.py
igap_bot/proto/ClientCountRoomHistory_pb2.py
igap_bot/proto/ClientGetDiscovery_pb2.py
igap_bot-0.1.6.dist-info/METADATA
igap_bot-0.1.6.dist-info/WHEEL
igap_bot-0.1.6.dist-info/top_level.txt
igap_bot-0.1.6.dist-info/RECORD
