Metadata-Version: 2.4
Name: igap-bot
Version: 0.1.6
Summary: Unofficial iGap Bot API client for Python
Home-page: https://github.com/EhsanGhorbany/igap-bot
Author: Ehsan
Author-email: Ehsan <Botkaplus@gmail.com>
License: MIT
Project-URL: Homepage, https://github.com/EhsanGhorbany/igap-bot
Project-URL: Source, https://github.com/EhsanGhorbany/igap-bot
Project-URL: Issues, https://github.com/EhsanGhorbany/igap-bot/issues
Requires-Python: >=3.8
Requires-Dist: protobuf<4.0.0,>=3.19.0
Requires-Dist: aiohttp>=3.8.0
Dynamic: author
Dynamic: home-page
Dynamic: requires-python
